myqueue/__init__.py
myqueue/__main__.py
myqueue/caching.py
myqueue/cli.py
myqueue/commands.py
myqueue/compare.py
myqueue/complete.py
myqueue/config.py
myqueue/daemon.py
myqueue/email.py
myqueue/errors.py
myqueue/hold.py
myqueue/info.py
myqueue/kick.py
myqueue/migration.py
myqueue/modify.py
myqueue/pretty.py
myqueue/py.typed
myqueue/queue.py
myqueue/remove.py
myqueue/resources.py
myqueue/resubmit.py
myqueue/selection.py
myqueue/states.py
myqueue/submitting.py
myqueue/syncronize.py
myqueue/task.py
myqueue/utils.py
myqueue/workflow.py
myqueue/schedulers/__init__.py
myqueue/schedulers/local.py
myqueue/schedulers/lsf.py
myqueue/schedulers/pbs.py
myqueue/schedulers/scheduler.py
myqueue/schedulers/slurm.py
myqueue/schedulers/test.py
myqueue/test/__init__.py
myqueue/test/caching_test.py
myqueue/test/command_test.py
myqueue/test/complete_test.py
myqueue/test/config_test.py
myqueue/test/conftest.py
myqueue/test/daemon_test.py
myqueue/test/error_msg_test.py
myqueue/test/flow1.py
myqueue/test/flow2.py
myqueue/test/hello.py
myqueue/test/local_test.py
myqueue/test/lock_test.py
myqueue/test/mod.py
myqueue/test/more_test.py
myqueue/test/mq_test.py
myqueue/test/name_test.py
myqueue/test/notify_test.py
myqueue/test/pp_test.py
myqueue/test/queue_test.py
myqueue/test/resources_test.py
myqueue/test/rst_test.py
myqueue/test/scheduler_test.py
myqueue/test/sqlite_test.py
myqueue/test/task_test.py
myqueue/test/utils_test.py
myqueue/test/workflow_test.py
myqueue-25.11.0.dist-info/licenses/LICENSE
myqueue-25.11.0.dist-info/METADATA
myqueue-25.11.0.dist-info/WHEEL
myqueue-25.11.0.dist-info/entry_points.txt
myqueue-25.11.0.dist-info/pbr.json
myqueue-25.11.0.dist-info/top_level.txt
myqueue-25.11.0.dist-info/RECORD
