Metadata-Version: 2.4
Name: myqueue
Version: 25.11.0
Summary: Frontend for SLURM/LSF/PBS
Maintainer-email: Jens Jørgen Mortensen <jjmo@dtu.dk>
License:                     GNU GENERAL PUBLIC LICENSE
Project-URL: homepage, https://myqueue.readthedocs.io
Project-URL: repository, https://gitlab.com/myqueue/myqueue
Project-URL: changelog, https://myqueue.readthedocs.io/releasenotes.html
Project-URL: docs, https://myqueue.readthedocs.io
Project-URL: issues, https://gitlab.com/myqueue/myqueue/-/issues
Project-URL: matrix, https://matrix.to/#/#myqueue:matrix.org
Classifier: Development Status :: 5 - Production/Stable
Classifier: Environment :: Console
Classifier: Intended Audience :: Developers
Classifier: Operating System :: Unix
Classifier: Programming Language :: Python :: 3
Classifier: Topic :: Scientific/Engineering
Requires-Python: >=3.9
License-File: LICENSE
Requires-Dist: rich
Requires-Dist: networkx
Requires-Dist: typing_extensions
Provides-Extra: dev
Requires-Dist: pytest; extra == "dev"
Dynamic: license-file
